dnn_tip/__init__.py
dnn_tip/apfd.py
dnn_tip/neuron_coverage.py
dnn_tip/prioritizers.py
dnn_tip/stable_kde.py
dnn_tip/surprise.py
dnn_tip-0.1.1.dist-info/LICENSE
dnn_tip-0.1.1.dist-info/METADATA
dnn_tip-0.1.1.dist-info/WHEEL
dnn_tip-0.1.1.dist-info/top_level.txt
dnn_tip-0.1.1.dist-info/RECORD
