Metadata-Version: 2.1
Name: dnn-tip
Version: 0.1.1
Summary: A collection of DNN test input prioritizers,in particular neuron coverage and surprise adequacy.
Home-page: https://github.com/testingautomated-usi/dnn-tip
Author: Michael Weiss
Author-email: michael.weiss@usi.ch
License: MIT
Platform: UNKNOWN
Classifier: Programming Language :: Python :: 3
Classifier: License :: OSI Approved :: MIT License
Classifier: Operating System :: OS Independent
License-File: LICENSE
Requires-Dist: psutil
Requires-Dist: scikit-learn
Requires-Dist: tqdm
Requires-Dist: packaging
Provides-Extra: lint
Requires-Dist: flake8 (==3.8.2) ; extra == 'lint'
Requires-Dist: black (==22.3.0) ; extra == 'lint'
Requires-Dist: isort (==5.6.4) ; extra == 'lint'
Requires-Dist: docstr-coverage (==2.2.0) ; extra == 'lint'
Provides-Extra: test
Requires-Dist: pytest (>=6.2.5) ; extra == 'test'
